pptx2md/__init__.py
pptx2md/initgen.py
pptx2md/main.py
pptx2md_re/__init__.py
pptx2md_re/main.py
pptx2md_re-0.0.1.dist-info/METADATA
pptx2md_re-0.0.1.dist-info/WHEEL
pptx2md_re-0.0.1.dist-info/top_level.txt
pptx2md_re-0.0.1.dist-info/RECORD
